python_scripts/constants.py
python_scripts/global_functions.py
python_scripts/smb_file_puller.py
python_scripts/smb_file_pusher.py
smb_copy_files-1.0.3.dist-info/METADATA
smb_copy_files-1.0.3.dist-info/WHEEL
smb_copy_files-1.0.3.dist-info/namespace_packages.txt
smb_copy_files-1.0.3.dist-info/top_level.txt
smb_copy_files-1.0.3.dist-info/zip-safe
smb_copy_files-1.0.3.dist-info/RECORD
