Metadata-Version: 2.1
Name: smb-copy-files
Version: 1.0.3
Home-page: 
Author: 
Author-email: 
Maintainer: 
Maintainer-email: 
Classifier: Development Status :: 3 - Alpha
Classifier: Programming Language :: Python
Requires-Dist: PySmbClient
